ankillins/__init__.py
ankillins/cli.py
ankillins/client.py
ankillins/constants.py
ankillins/errors.py
ankillins/main.py
ankillins/templates/back.html
ankillins-0.0.1.dist-info/LICENSE
ankillins-0.0.1.dist-info/METADATA
ankillins-0.0.1.dist-info/WHEEL
ankillins-0.0.1.dist-info/entry_points.txt
ankillins-0.0.1.dist-info/top_level.txt
ankillins-0.0.1.dist-info/RECORD
