Metadata-Version: 2.1
Name: ankillins
Version: 0.0.1
Summary: Anki cards generating from CollinsDictionary pages
Home-page: UNKNOWN
Author: Damir Chanyshev
Author-email: hairygeek@yandex.com
License: UNKNOWN
Project-URL: Bug Tracker, https://github.com/hairygeek/ankillins
Project-URL: Documentation, https://github.com/hairygeek/ankillins
Project-URL: Source Code, https://github.com/hairygeek/ankillins
Keywords: anki card generation collins
Platform: UNKNOWN
Requires-Dist: colorama (>=0.4.3)
Requires-Dist: click (>=7.1.2)
Requires-Dist: requests (>=2.24.0)
Requires-Dist: jsonschema (>=3.2.0)
Requires-Dist: yarl (>=1.4.2)
Requires-Dist: lxml (>=4.5.2)
Requires-Dist: jinja2 (>=2.11.2)
Requires-Dist: tenacity (>=6.2.0)
